ALU.v
module ALU(
    input [1:0] alu_op,
    input [4:0] op_func,   //FUNC3 + FUNC7[5] + OPCODE[5] -> aka {OPCODE[5],instr[30],instr[14:12]}
    input [31:0] d1,
    input [31:0] d2,
    output reg[31:0] dout,
    output reg   b_success=0
);

reg is_add=0;
reg is_sub=0;
reg is_sll=0;
reg is_srl=0;
reg is_sra=0;
reg is_or=0;
reg is_and=0;
reg is_xor=0;

always @(*) begin
    is_add<=0;
    is_sub<=0;
    is_sll<=0;
    is_srl<=0;
    is_sra<=0;
    is_or<=0;
    is_and<=0;
    is_xor<=0;
    if(alu_op==2'b00)begin
        case(op_func[2:0])
            3'b000: //if R type(op_func[4]=1),op_func[3]=1(sub) op_func[3]=0(add)
                    //if I type(op_func[4]=0),is addi.
                    begin
                         is_add <= (op_func[4]==0 || op_func[4:3] == 2'b10) ? 1 : 0;
                         is_sub <= (op_func[4:3]==2'b11) ? 1 : 0;
                    end
            3'b001: is_sll<=1;
            3'b100: is_xor<=1;
            3'b101: begin if(op_func[3]) is_sra<=1; else  is_srl<=1;  end
            3'b110: is_or<=1;
            3'b111: is_and<=1;
        endcase
    end
    else if(alu_op==2'b01)begin
        is_add<=1;
    end
    else if(alu_op==2'b11)begin
        is_sub<=1;
    end
end

always@(*)begin
    if(is_add)      dout <= $signed(d1) + $signed(d2);
    else if(is_and) dout <= d1 & d2;
    else if(is_or)  dout <= d1 | d2;
    else if(is_sll) dout <= d1 << d2;
    else if(is_sra) dout <= $signed(d1) >>> d2;
    else if(is_srl) dout <= d1 >> d2;
    else if(is_sub) dout <= $signed(d1) - $signed(d2);
    else if(is_xor) dout <= d1 ^ d2;
end

reg b_lt=0;
reg b_ge=0;
reg b_eq=0;
//branch judge.
always@(*)begin
    if(alu_op==2'b11)
    begin
        if(dout==0)begin
            b_eq<=1;
        end
        else b_eq <= 0;

        if(dout[31]==1'b1)begin
            b_lt<=1;
        end
        else b_lt <= 0;

        if(dout[31]==0&&dout>=0) b_ge <= 1;
        else  b_ge <= 0;
    end
    else begin
        b_eq<=0;
        b_lt<=0;
        b_ge<=0;
    end

end

always@(*)
begin
    if(op_func[2:0]==3'b000)begin
        b_success<=b_eq;
    end
    else if(op_func[2:0]==3'b100)begin
        b_success<=b_lt;
    end
    else if(op_func[2:0]==3'b101)begin
        b_success<=b_ge;
    end
    else b_success<=0;
end

endmodule

ALU_tb.v
module ALU_tb();
reg clk=0;
always begin
    #1 clk = ~clk;
end

reg [31:0] num1;
reg [31:0] num2;
wire [31:0] out;
reg [1:0] alu_op=2'b11;
reg [4:0] op_func;
wire b_succuss;

ALU _inst_test_ALU(
    alu_op,
    op_func,
    num1,
    num2,
    out,
    b_succuss
);

//  Test  these  operations:
//  num1 and num2  all signed.
//  add  32'd 200 + 32'd 12000
//  add  32'h 7fffffff +  32'h1
//  sub  32'd 1000 - 32'd  112
//  addi  32'd 500 + 32'd -1000
//  sub  32'd 1    - 32'd 9

//  sll  32'h 00007fff << 0
//  sll  32'h 00007fff << 31

//  srl  32'h 7fff0000 >> 4
//  srl  32'h 8fff0000 >> 12

//  sra  32'h 7000ffff >> 5
//  sra  32'h 8000ffff >> 31

//  and  32'h ffff0000 &  32'hf0000000
//  or   32'h 0000ffff |  32'hffff0000
//  xor  32'h f0f00f0f ^  32'hffffffff

initial begin
    #10 op_func <= 5'b10000;
    num1 <= 32'd200;
    num2 <= 32'd12000;
    #10 op_func <= 5'b10000;
    num1 <= 32'h7fffffff;
    num2 <= 32'd1;
    #10 op_func <= 5'b11000;
    num1 <= 32'd1000;
    num2 <= 32'd112;
    #10 op_func <= 5'b00000;
    num1 <= 32'd500;
    num2 <= -32'd1000;
    #10 op_func <= 5'b11000;  //sub 1 , 9
    num1 <= 32'd1;
    num2 <= 32'd9;
    //sll
    #10 op_func <= 5'b10001;
    num1 <= 32'h00007fff;
    num2 <= 32'd0;
    //sll 31
    #10 op_func <= 5'b10001;
    num1 <= 32'h00007fff;
    num2 <= 32'd31;
    //srl 4
    #10 op_func <= 5'b10101;
    num1 <= 32'h00007fff;
    num2 <= 32'd4;
    //srl
    #10 op_func <= 5'b10101;
    num1 <= 32'h00007fff;
    num2 <= 32'd12;

    //sra
    #10 op_func <= 5'b11101;
    num1 <= 32'h7000ffff;
    num2 <= 32'd5;

    //sra
    #10 op_func <= 5'b01101;
    num1 <= 32'hf000ffff;
    num2 <= 32'd31;

    //and
    #10 op_func <= 5'b01111;
    num1 <= 32'hffff0000;
    num2 <= 32'hf0000000;

    //or
    #10 op_func <= 5'b00110;
    num1 <= 32'h0000ffff;
    num2 <= 32'hffff0000;

    //xor
    #10 op_func <= 5'b10100;
    num1 <= 32'hf0f00f0f;
    num2 <= 32'hffffffff;

//  beq  32'hffffffff == 32'hffffffff    T
//  beq  -32'd1 == 32'd1                 F

//  blt  32'd50 <  32'd51                T
//  blt  32'd52 <  32'd50                F

//  bge  32'd0 >= 32'd0                  T
//  bge  32'hfffffff0 >=  32'hffffffff   F

    //beq
    #10
    op_func <= 5'b10000;
    num1 <= 32'hffffffff;
    num2 <= 32'hffffffff;
    #10
    op_func <= 5'b10000;
    num1 <= -32'd1;
    num2 <=  32'd1;

    //blt
    #10
    op_func <= 5'b11100;
    num1 <= 32'd50;
    num2 <= 32'd51;
    #10
    op_func <= 5'b11100;
    num1 <= 32'd52;
    num2 <= 32'd50;

    //bge
    #10
    op_func <= 5'b10101;
    num1 <= 32'd0;
    num2 <= 32'd0;
    #10
    op_func <= 5'b10101;
    num1 <= 32'hfffffff0;
    num2 <= 32'hffffffff;

    #100 $finish;
end

initial begin
        $dumpfile("alu_tb.vcd");
        $dumpvars(0,ALU_tb);
end


endmodule

alu_tb.vcd
$date
	Fri Sep 01 22:51:56 2023
$end
$version
	Icarus Verilog
$end
$timescale
	1s
$end
$scope module ALU_tb $end
$var wire 32 ! out [31:0] $end
$var wire 1 " b_succuss $end
$var reg 2 # alu_op [1:0] $end
$var reg 1 $ clk $end
$var reg 32 % num1 [31:0] $end
$var reg 32 & num2 [31:0] $end
$var reg 5 ' op_func [4:0] $end
$scope module _inst_test_ALU $end
$var wire 2 ( alu_op [1:0] $end
$var wire 32 ) d1 [31:0] $end
$var wire 32 * d2 [31:0] $end
$var wire 5 + op_func [4:0] $end
$var reg 1 , b_eq $end
$var reg 1 - b_ge $end
$var reg 1 . b_lt $end
$var reg 1 " b_success $end
$var reg 32 / dout [31:0] $end
$var reg 1 0 is_add $end
$var reg 1 1 is_and $end
$var reg 1 2 is_or $end
$var reg 1 3 is_sll $end
$var reg 1 4 is_sra $end
$var reg 1 5 is_srl $end
$var reg 1 6 is_sub $end
$var reg 1 7 is_xor $end
$upscope $end
$upscope $end
$enddefinitions $end
$comment Show the parameter values. $end
$dumpall
$end
#0
$dumpvars
07
16
05
04
03
02
01
00
bx /
0.
0-
0,
bx +
bx *
bx )
b11 (
bx '
bx &
bx %
0$
b11 #
0"
bx !
$end
#1
1$
#2
0$
#3
1$
#4
0$
#5
1$
#6
0$
#7
1$
#8
0$
#9
1$
#10
1.
b11111111111111111101000111101000 !
b11111111111111111101000111101000 /
16
b10111011100000 &
b10111011100000 *
b11001000 %
b11001000 )
b10000 '
b10000 +
0$
#11
1$
#12
0$
#13
1$
#14
0$
#15
1$
#16
0$
#17
1$
#18
0$
#19
1$
#20
1-
0.
b1111111111111111111111111111110 !
b1111111111111111111111111111110 /
b1 &
b1 *
b1111111111111111111111111111111 %
b1111111111111111111111111111111 )
0$
#21
1$
#22
0$
#23
1$
#24
0$
#25
1$
#26
0$
#27
1$
#28
0$
#29
1$
#30
b1101111000 !
b1101111000 /
16
b1110000 &
b1110000 *
b1111101000 %
b1111101000 )
b11000 '
b11000 +
0$
#31
1$
#32
0$
#33
1$
#34
0$
#35
1$
#36
0$
#37
1$
#38
0$
#39
1$
#40
b10111011100 !
b10111011100 /
16
b11111111111111111111110000011000 &
b11111111111111111111110000011000 *
b111110100 %
b111110100 )
b0 '
b0 +
0$
#41
1$
#42
0$
#43
1$
#44
0$
#45
1$
#46
0$
#47
1$
#48
0$
#49
1$
#50
0-
1.
b11111111111111111111111111111000 !
b11111111111111111111111111111000 /
16
b1001 &
b1001 *
b1 %
b1 )
b11000 '
b11000 +
0$
#51
1$
#52
0$
#53
1$
#54
0$
#55
1$
#56
0$
#57
1$
#58
0$
#59
1$
#60
1-
0.
b111111111111111 !
b111111111111111 /
16
b0 &
b0 *
b111111111111111 %
b111111111111111 )
b10001 '
b10001 +
0$
#61
1$
#62
0$
#63
1$
#64
0$
#65
1$
#66
0$
#67
1$
#68
0$
#69
1$
#70
b111111111100000 !
b111111111100000 /
b11111 &
b11111 *
0$
#71
1$
#72
0$
#73
1$
#74
0$
#75
1$
#76
0$
#77
1$
#78
0$
#79
1$
#80
b111111111111011 !
b111111111111011 /
1"
16
b100 &
b100 *
b10101 '
b10101 +
0$
#81
1$
#82
0$
#83
1$
#84
0$
#85
1$
#86
0$
#87
1$
#88
0$
#89
1$
#90
b111111111110011 !
b111111111110011 /
b1100 &
b1100 *
0$
#91
1$
#92
0$
#93
1$
#94
0$
#95
1$
#96
0$
#97
1$
#98
0$
#99
1$
#100
b1110000000000001111111111111010 !
b1110000000000001111111111111010 /
16
b101 &
b101 *
b1110000000000001111111111111111 %
b1110000000000001111111111111111 )
b11101 '
b11101 +
0$
#101
1$
#102
0$
#103
1$
#104
0$
#105
1$
#106
0$
#107
1$
#108
0$
#109
1$
#110
0"
0-
1.
b11110000000000001111111111100000 !
b11110000000000001111111111100000 /
16
b11111 &
b11111 *
b11110000000000001111111111111111 %
b11110000000000001111111111111111 )
b1101 '
b1101 +
0$
#111
1$
#112
0$
#113
1$
#114
0$
#115
1$
#116
0$
#117
1$
#118
0$
#119
1$
#120
1-
0.
b1111111111110000000000000000 !
b1111111111110000000000000000 /
16
b11110000000000000000000000000000 &
b11110000000000000000000000000000 *
b11111111111111110000000000000000 %
b11111111111111110000000000000000 )
b1111 '
b1111 +
0$
#121
1$
#122
0$
#123
1$
#124
0$
#125
1$
#126
0$
#127
1$
#128
0$
#129
1$
#130
b11111111111111111 !
b11111111111111111 /
16
b11111111111111110000000000000000 &
b11111111111111110000000000000000 *
b1111111111111111 %
b1111111111111111 )
b110 '
b110 +
0$
#131
1$
#132
0$
#133
1$
#134
0$
#135
1$
#136
0$
#137
1$
#138
0$
#139
1$
#140
1"
0-
1.
b11110000111100000000111100010000 !
b11110000111100000000111100010000 /
16
b11111111111111111111111111111111 &
b11111111111111111111111111111111 *
b11110000111100000000111100001111 %
b11110000111100000000111100001111 )
b10100 '
b10100 +
0$
#141
1$
#142
0$
#143
1$
#144
0$
#145
1$
#146
0$
#147
1$
#148
0$
#149
1$
#150
1-
0.
1,
b0 !
b0 /
1"
16
b11111111111111111111111111111111 %
b11111111111111111111111111111111 )
b10000 '
b10000 +
0$
#151
1$
#152
0$
#153
1$
#154
0$
#155
1$
#156
0$
#157
1$
#158
0$
#159
1$
#160
0"
0-
1.
0,
b11111111111111111111111111111110 !
b11111111111111111111111111111110 /
b1 &
b1 *
0$
#161
1$
#162
0$
#163
1$
#164
0$
#165
1$
#166
0$
#167
1$
#168
0$
#169
1$
#170
b11111111111111111111111111111111 !
b11111111111111111111111111111111 /
1"
16
b110011 &
b110011 *
b110010 %
b110010 )
b11100 '
b11100 +
0$
#171
1$
#172
0$
#173
1$
#174
0$
#175
1$
#176
0$
#177
1$
#178
0$
#179
1$
#180
0"
1-
0.
b10 !
b10 /
b110010 &
b110010 *
b110100 %
b110100 )
0$
#181
1$
#182
0$
#183
1$
#184
0$
#185
1$
#186
0$
#187
1$
#188
0$
#189
1$
#190
1,
b0 !
b0 /
1"
16
b0 &
b0 *
b0 %
b0 )
b10101 '
b10101 +
0$
#191
1$
#192
0$
#193
1$
#194
0$
#195
1$
#196
0$
#197
1$
#198
0$
#199
1$
#200
0"
0-
1.
0,
b11111111111111111111111111110001 !
b11111111111111111111111111110001 /
b11111111111111111111111111111111 &
b11111111111111111111111111111111 *
b11111111111111111111111111110000 %
b11111111111111111111111111110000 )
0$
