core/WB_Mux.v
module WB_Mux(
    input [1:0] s_mem_to_reg,
    input [31:0] DMem_Out,
    input [31:0] ALU_Result,
    input [31:0] PC,
    input [31:0] Imm_Out,
    output reg [31:0] Data_Out=0
);

always@(*)begin
    case(s_mem_to_reg)
        2'b00:Data_Out<=ALU_Result;
        2'b01:Data_Out<=DMem_Out;
        2'b10:Data_Out<=PC+4;
        2'b11:Data_Out<=Imm_Out;
    endcase
end

endmodule

core/DMem_Interface.v
module DMem_Interface(
    input clk,
    input rst_n,
    input  wen,
    input  ren,
    input [31:0] wd,
    input [31:0] addr,
    output reg [31:0] rd_out=0,
    output reg dmem_rdy=0
);
reg [7:0] D_Cache [0:255];

always@(*)begin
    if(ren)begin
        rd_out<={D_Cache[addr],D_Cache[addr+1],D_Cache[addr+2],D_Cache[addr+3]};
        dmem_rdy<=1;
    end
    else begin
        rd_out<=rd_out;
        dmem_rdy<=0;
    end
end

integer i;
always@(posedge clk or negedge rst_n) begin
    if(!rst_n) begin
        for(i=0;i<256;i++) D_Cache[i]<=0;
    end
    else if(wen)begin
        D_Cache[addr]  <=wd[24+:8];
        D_Cache[addr+1]<=wd[16+:8];
        D_Cache[addr+2]<=wd[8+:8];
        D_Cache[addr+3]<=wd[0+:8];
    end
end

endmodule

InstrDiff.v
//根据输入的instr[6:0] 区分 R type/I type/ U type/ UJ type/ S type/ SB type
module InstrDiff(
    input [6:0] instr_op,
    output  reg  [2:0]sel
);

always@(*)begin
    if(instr_op[6:2]==5'b00000||instr_op[6:2]==5'b00100||instr_op[6:2]==5'b00110||instr_op[6:2]==5'b11001||instr_op[6:2]==5'b11100)
    begin
        sel <= 3'b000;   //I type.
    end
    else if(instr_op[6:2]==5'b00101||instr_op[6:2]==5'b01101)begin
        sel <= 3'b001;   //U type
    end
    else if(instr_op[6:2]==5'b11011) begin
        sel <= 3'b010;   // UJ
    end
    else if(instr_op[6:2]==5'b01000) begin
        sel <= 3'b011;   //S
    end
    else if(instr_op[6:2]==5'b11000) begin
        sel <= 3'b100;  //SB
    end
    else if(instr_op[6:2]==5'b01100||instr_op[6:2]==5'b01110) begin
        sel <= 3'b101;         //R
    end
    else begin
        sel <= 3'b111;  //Unknown.
    end
end
endmodule

Control.v
//Generate  Branch/MemRead/MemToReg/ALUOp/MemWrite/ALUSrc/Reg Signals.
module Control(
    input [6:0] opcode,
    output reg s_branch=0,
    output reg s_mem_read=0,   // if 1,read Mem and write to RegFile,else write the result of ALU to RegFile.
    output reg [1:0] s_mem_to_reg=0,  //if mem_to_reg==2,write PC+4 into reg.
    output reg [1:0] s_alu_op=2'b0,   //00->R type I type | 01 add : Load(I) Store(SB) auipc(UJ)  | 10 no operation (lui) jal(UJ) jalr(I) | 11: branch sub
    output reg s_mem_write=0,
    output reg s_alu_src1=0,  //0->rs1 1->PC(auipc)
    output reg s_alu_src2=0,  //0->rs2 1->Imm
    output reg s_reg_write=0,
    output reg [1:0]  s_pc_sel=0  //00->PC=PC+4  01->branch  10->PC=PC+Imm(jal) 11->PC=R[rs1]+Imm(jalr)
);

wire [2:0] opcode_sel;

InstrDiff _get_opcode_sel(
    opcode,
    opcode_sel
);

always@(*)begin
    if(opcode_sel==3'b100)begin
        s_pc_sel<=2'b01;
    end
    else if(opcode_sel==3'b010) begin
        s_pc_sel<=2'b10;
    end
    else if(opcode[6:2]==5'b11001) begin
        s_pc_sel<=2'b11;
    end
    else begin
        s_pc_sel<=2'b00;
    end
end

// generate branch
always @(*) begin
    if(opcode_sel==3'b100) begin
        s_branch<=1;
    end
    else begin
        s_branch<=0;
    end
end

//for load
always@(*)begin
    if(opcode[6:2]==5'b00000)
    begin
        s_mem_read<=1;
    end
    else begin
        s_mem_read<=0;
    end
end

// s_mem_to_reg Load/jal jalr  00->ALU result. 01->MEM Output.(load) 10->PC+4(jal jalr)  11->Imm(lui)
always@(*)begin
    if(opcode[6:2]==5'b00000)begin
        s_mem_to_reg<=2'b01;
    end
    else if(opcode[6:2]==5'b11001||opcode[6:2]==5'b11011)begin
        s_mem_to_reg<=2'b10;
    end
    else if(opcode[6:2]==5'b01101)begin
        s_mem_to_reg<=2'b11;
    end
    else begin
        s_mem_to_reg<=2'b00;
    end
end

always@(*)begin
    if(opcode_sel==3'b011)begin   //Stype.
        s_mem_write<=1;
    end
    else begin
        s_mem_write<=0;
    end
end

always@(*)begin
    if(opcode_sel==3'b101 || opcode_sel==3'b100) begin   //Rtype,SB type use rs2
        s_alu_src2<=0;//not use ImmGen.
    end
    else begin
        s_alu_src2<=1;
    end
end

always@(*)begin   //auipc->00101
    if(opcode[6:2]==5'b00101)begin
        s_alu_src1<=1;
    end
    else begin
        s_alu_src1<=0;
    end
end

always@(*)begin    // set 1 if opcode is R type\ U type\ I type\UJ
    if(opcode_sel==3'b011||opcode_sel==3'b100)begin
        s_reg_write<=0;
    end
    else begin
        s_reg_write<=1;
    end

end

always@(*)begin
    if(opcode_sel==3'b100) begin
        //branch
        s_alu_op<=2'b11;
    end
    else if(opcode[6:2]==5'b01101 || opcode[6:2] == 5'b11001 || opcode_sel==3'b010) begin
        s_alu_op<=2'b10;
    end
    else if(opcode[6:2]==5'b00000 || opcode_sel==3'b011 || opcode[6:2] == 5'b00101) begin
        s_alu_op<=2'b01;
    end
    else if(opcode_sel==3'b000||opcode_sel==3'b101) begin
        s_alu_op<=2'b00;
    end
    else begin
        s_alu_op<=2'b10;
    end
end

endmodule

ALU.v
module ALU(
    input [1:0] alu_op,
    input [4:0] op_func,   //FUNC3 + FUNC7[5] + OPCODE[5] -> aka {OPCODE[5],instr[30],instr[14:12]}
    input [31:0] d1,
    input [31:0] d2,
    output reg[31:0] dout,
    output reg   b_success=0
);

reg is_add=0;
reg is_sub=0;
reg is_sll=0;
reg is_srl=0;
reg is_sra=0;
reg is_or=0;
reg is_and=0;
reg is_xor=0;

always @(*) begin
    is_add<=0;
    is_sub<=0;
    is_sll<=0;
    is_srl<=0;
    is_sra<=0;
    is_or<=0;
    is_and<=0;
    is_xor<=0;
    if(alu_op==2'b00)begin
        case(op_func[2:0])
            3'b000: //if R type(op_func[4]=1),op_func[3]=1(sub) op_func[3]=0(add)
                    //if I type(op_func[4]=0),is addi.
                    begin
                         is_add <= (op_func[4]==0 || op_func[4:3] == 2'b10) ? 1 : 0;
                         is_sub <= (op_func[4:3]==2'b11) ? 1 : 0;
                    end
            3'b001: is_sll<=1;
            3'b100: is_xor<=1;
            3'b101: begin if(op_func[3]) is_sra<=1; else  is_srl<=1;  end
            3'b110: is_or<=1;
            3'b111: is_and<=1;
        endcase
    end
    else if(alu_op==2'b01)begin
        is_add<=1;
    end
    else if(alu_op==2'b11)begin
        is_sub<=1;
    end
end

always@(*)begin
    if(is_add)      dout <= $signed(d1) + $signed(d2);
    else if(is_and) dout <= d1 & d2;
    else if(is_or)  dout <= d1 | d2;
    else if(is_sll) dout <= d1 << d2;
    else if(is_sra) dout <= $signed(d1) >>> d2;
    else if(is_srl) dout <= d1 >> d2;
    else if(is_sub) dout <= $signed(d1) - $signed(d2);
    else if(is_xor) dout <= d1 ^ d2;
end

reg b_lt=0;
reg b_ge=0;
reg b_eq=0;
//branch judge.
always@(*)begin
    if(alu_op==2'b11)
    begin
        if(dout==0)begin
            b_eq<=1;
        end
        else b_eq <= 0;

        if(dout[31]==1'b1)begin
            b_lt<=1;
        end
        else b_lt <= 0;

        if(dout[31]==0&&dout>=0) b_ge <= 1;
        else  b_ge <= 0;
    end
    else begin
        b_eq<=0;
        b_lt<=0;
        b_ge<=0;
    end

end

always@(*)
begin
    if(op_func[2:0]==3'b000)begin
        b_success<=b_eq;
    end
    else if(op_func[2:0]==3'b100)begin
        b_success<=b_lt;
    end
    else if(op_func[2:0]==3'b101)begin
        b_success<=b_ge;
    end
    else b_success<=0;
end

endmodule

ImmGen.v
module ImmGen(
    input [31:0] instr,
    output reg [31:0] imm
);

wire  [2:0]  opcode_sel;  // I type(instr[31:20])  S type (instr[31:25],instr[11:7])
// SB type (instr[31:25] -> imm[12|10:5]   instr[11:7]-> imm[4:1|11])
// U type  (instr[31:12])
// UJ type (instr[31:12]->imm[20|10:1|11|19:12])
wire   high_bit = instr[31];
wire [19:0]  all_high=20'hfffff;
wire [19:0]  all_low=20'h00000;

InstrDiff _get_instr_diff(
    instr[6:0],
    opcode_sel
);

always@(*)begin
    case (opcode_sel)
        3'b000:begin
            imm <= {(high_bit)?all_high:all_low,instr[31:20]};
        end
        3'b001:
            imm <= {instr[31:12],12'h000};
        3'b010:
            imm <= {(high_bit)?11'h7ff:11'h000,instr[31],instr[19:12],instr[20],instr[30:21],1'b0};
        3'b011:
            imm <= {(high_bit)?all_high:all_low,instr[31:25],instr[11:7]};
        3'b100:
            imm <= {(high_bit)?19'h7ffff:19'h00000,instr[31],instr[7],instr[30:25],instr[11:8],1'b0};
        default:
            imm <= 32'b0;
    endcase
end
endmodule

core/RegFile.v
module RegFile(
    input clk,
    input rst_n,
    input [4:0] rs1,
    input [4:0] rs2,
    input [4:0] rd,
    output reg [31:0] R1=0,
    output reg [31:0] R2=0,
    input wen,
    input [31:0] Rd_dat
);

reg [31:0] regs [0:31];

always@(*)begin
    if(rs1==0)
    begin
        R1<=0;
    end
    // else if(rs1==rd&&wen==1)begin
    //     R1<=Rd_dat;
    // end
    else
        R1<=regs[rs1];
end

always@(*)begin
    if(rs2==0)
    begin
        R2<=0;
    end
    // else if(rs2==rd&&wen==1)begin
    //     R2<=Rd_dat;
    // end
    else
        R2<=regs[rs2];
end

integer i;
always @(posedge clk or negedge rst_n) begin
    if(!rst_n)
    begin
        for(i=0;i<32;i++)
            regs[i]<=0;
    end
    else if(wen&&rd!=0)
    begin
        regs[rd] <= Rd_dat;
    end
end

endmodule

IMem_Interface.v
module IMem_Interface(
    input clk,
    input [31:0] PC,
    output reg rdy,  // instr ready.
    output reg [31:0] INSTR=0
);

reg [31:0] I_Cache [0:255];

initial begin
    $readmemh("I_Cache_Test.hex",I_Cache);
end

reg [3:0] counter=0;
always @(posedge clk) begin
    if(counter==1)begin
        INSTR<=I_Cache[PC];
        counter<=0;
        rdy<=1;
    end
    else begin
        INSTR<=INSTR;
        counter<=counter+1;
        rdy<=0;
    end
end

endmodule

core/PC_Control.v
module PC_Control(
    input clk,
    input [1:0] PC_Sel,  //branch:PC=PC+Imm.  jal:PC=PC+imm.  jalr:PC=R_rs1+Imm
    // if PC_Sel==00(default),PC=PC+4.  else if 01: branch PC = PC + Imm or PC + 4 else if 10: PC=PC+Imm.
    // 11:PC=R_rs1+Imm.
    input s_branch, //if 1,branch jump.
    input [31:0]  Imm,
    input [31:0] R_rs1,
    output reg [31:0] PC=0
);

always @(posedge clk) begin
    case(PC_Sel)
        2'b00:begin
            PC<=PC+4;
        end
        2'b01:begin
            PC<=(s_branch)?PC+Imm:PC+4;
        end
        2'b10:begin
            PC<=PC+Imm;
        end
        2'b11:begin
            PC<=R_rs1+Imm;
        end
    endcase
end

endmodule

core/CPU_Top.v
module CPU_Top(
    input clk,
    input rst_n
);

reg [2:0] cpu_state=0;
localparam IF = 0;
localparam ID = 1;
localparam EX = 2;
localparam MEM = 3;
localparam WB = 4;
reg pc_clk=0;
wire imem_rdy;
wire [31:0] PC;
wire [31:0] INSTR;

PC_Control _inst_pc(
    pc_clk,
    s_pc_sel,
    s_branch&branch_result,
    Imm_Out,
    R1,
    PC
);

IMem_Interface _inst_imem(
    clk,
    PC,
    imem_rdy,
    INSTR
);

//ALU signals:
wire [31:0] R1;
wire [31:0] R2;
reg  RegFile_wen=0;
wire [31:0] ALU_Result;
wire  branch_result;

RegFile _inst_regfile(
    clk,
    rst_n,
    INSTR[19:15],
    INSTR[24:20],
    INSTR[11:7],
    R1,
    R2,
    RegFile_wen,
    Data_Out
);

wire [31:0] Imm_Out;
ImmGen _inst_immgen(
    INSTR,
    Imm_Out
);

ALU _inst_alu(
    s_alu_op,
    {INSTR[5],INSTR[30],INSTR[14:12]},
    (s_alu_src1)?PC:R1,
    (s_alu_src2)?Imm_Out:R2,
    ALU_Result,
    branch_result
);

// CPU Control Signals:
wire s_branch;
wire s_mem_read;
wire [1:0] s_mem_to_reg;
wire [1:0] s_alu_op;
wire s_mem_write;
wire s_alu_src1;
wire s_alu_src2;
wire s_reg_write;
wire [1:0] s_pc_sel;

Control _inst_control(
    INSTR[6:0],
    s_branch,
    s_mem_read,
    s_mem_to_reg,
    s_alu_op,
    s_mem_write,
    s_alu_src1,
    s_alu_src2,
    s_reg_write,
    s_pc_sel
);

// DMem Read and Write Signals:
reg s_ren=0;
reg s_wen=0;
wire [31:0] DMem_Out;
wire dmem_rdy;

DMem_Interface _inst_dmem(
    clk,
    rst_n,
    s_wen,
    s_ren,
    R2,
    ALU_Result,
    DMem_Out,
    dmem_rdy
);

wire [31:0] Data_Out;
WB_Mux _inst_wbmux(
    s_mem_to_reg,
    DMem_Out,
    ALU_Result,
    PC,
    Imm_Out,
    Data_Out
);

always @(posedge clk) begin
    case(cpu_state)
        IF:begin
            RegFile_wen<=0;
            pc_clk<=0;

            if(imem_rdy)begin
                cpu_state<=ID;
            end
        end
        ID:
            cpu_state<=EX;
        EX:begin
            if(s_mem_read) s_ren<=1;
            else if(s_mem_write) s_wen <= 1;
            cpu_state<=MEM;
            end
        MEM:begin
            if(s_mem_read)begin
                if(dmem_rdy)cpu_state<=WB;
            end
            else
                cpu_state<=WB;    //waiting for data ready.
            s_ren<=0;
            s_wen<=0;
        end
        WB:
            begin
                if(s_reg_write)    // Stype and SB do not write back.
                    RegFile_wen<=1;
                pc_clk<=1;
                cpu_state<=IF;
            end
    endcase
end

endmodule

testbench/Top_tb.v
module Top_tb();
reg clk=0;
reg rst_n=1;
always #2 clk=~clk;

CPU_Top _inst_cpu_top(
    clk,
    rst_n
);
initial begin
        rst_n <= 0;
        #2 rst_n <= 1;
        #1000 $finish;
end

initial begin
        $dumpfile("cpu_top.vcd");
        $dumpvars(0,Top_tb);
end

endmodule

cpu_top.vcd
$date
	Sun Sep 03 20:56:17 2023
$end
$version
	Icarus Verilog
$end
$timescale
	1s
$end
$scope module Top_tb $end
$var reg 1 ! clk $end
$var reg 1 " rst_n $end
$scope module _inst_cpu_top $end
$var wire 1 ! clk $end
$var wire 1 " rst_n $end
$var wire 1 # s_reg_write $end
$var wire 2 $ s_pc_sel [1:0] $end
$var wire 1 % s_mem_write $end
$var wire 2 & s_mem_to_reg [1:0] $end
$var wire 1 ' s_mem_read $end
$var wire 1 ( s_branch $end
$var wire 1 ) s_alu_src2 $end
$var wire 1 * s_alu_src1 $end
$var wire 2 + s_alu_op [1:0] $end
$var wire 1 , imem_rdy $end
$var wire 1 - dmem_rdy $end
$var wire 1 . branch_result $end
$var wire 32 / R2 [31:0] $end
$var wire 32 0 R1 [31:0] $end
$var wire 32 1 PC [31:0] $end
$var wire 32 2 Imm_Out [31:0] $end
$var wire 32 3 INSTR [31:0] $end
$var wire 32 4 Data_Out [31:0] $end
$var wire 32 5 DMem_Out [31:0] $end
$var wire 32 6 ALU_Result [31:0] $end
$var parameter 32 7 EX $end
$var parameter 32 8 ID $end
$var parameter 32 9 IF $end
$var parameter 32 : MEM $end
$var parameter 32 ; WB $end
$var reg 1 < RegFile_wen $end
$var reg 3 = cpu_state [2:0] $end
$var reg 1 > pc_clk $end
$var reg 1 ? s_ren $end
$var reg 1 @ s_wen $end
$scope module _inst_alu $end
$var wire 32 A d1 [31:0] $end
$var wire 32 B d2 [31:0] $end
$var wire 5 C op_func [4:0] $end
$var wire 2 D alu_op [1:0] $end
$var reg 1 E b_eq $end
$var reg 1 F b_ge $end
$var reg 1 G b_lt $end
$var reg 1 . b_success $end
$var reg 32 H dout [31:0] $end
$var reg 1 I is_add $end
$var reg 1 J is_and $end
$var reg 1 K is_or $end
$var reg 1 L is_sll $end
$var reg 1 M is_sra $end
$var reg 1 N is_srl $end
$var reg 1 O is_sub $end
$var reg 1 P is_xor $end
$upscope $end
$scope module _inst_control $end
$var wire 7 Q opcode [6:0] $end
$var wire 3 R opcode_sel [2:0] $end
$var reg 2 S s_alu_op [1:0] $end
$var reg 1 * s_alu_src1 $end
$var reg 1 ) s_alu_src2 $end
$var reg 1 ( s_branch $end
$var reg 1 ' s_mem_read $end
$var reg 2 T s_mem_to_reg [1:0] $end
$var reg 1 % s_mem_write $end
$var reg 2 U s_pc_sel [1:0] $end
$var reg 1 # s_reg_write $end
$scope module _get_opcode_sel $end
$var wire 7 V instr_op [6:0] $end
$var reg 3 W sel [2:0] $end
$upscope $end
$upscope $end
$scope module _inst_dmem $end
$var wire 32 X addr [31:0] $end
$var wire 1 ! clk $end
$var wire 1 ? ren $end
$var wire 1 " rst_n $end
$var wire 1 @ wen $end
$var wire 32 Y wd [31:0] $end
$var reg 1 - dmem_rdy $end
$var reg 32 Z rd_out [31:0] $end
$var integer 32 [ i [31:0] $end
$upscope $end
$scope module _inst_imem $end
$var wire 1 ! clk $end
$var wire 32 \ PC [31:0] $end
$var reg 32 ] INSTR [31:0] $end
$var reg 4 ^ counter [3:0] $end
$var reg 1 , rdy $end
$upscope $end
$scope module _inst_immgen $end
$var wire 20 _ all_high [19:0] $end
$var wire 20 ` all_low [19:0] $end
$var wire 32 a instr [31:0] $end
$var wire 3 b opcode_sel [2:0] $end
$var wire 1 c high_bit $end
$var reg 32 d imm [31:0] $end
$scope module _get_instr_diff $end
$var wire 7 e instr_op [6:0] $end
$var reg 3 f sel [2:0] $end
$upscope $end
$upscope $end
$scope module _inst_pc $end
$var wire 32 g Imm [31:0] $end
$var wire 2 h PC_Sel [1:0] $end
$var wire 1 > clk $end
$var wire 1 i s_branch $end
$var wire 32 j R_rs1 [31:0] $end
$var reg 32 k PC [31:0] $end
$upscope $end
$scope module _inst_regfile $end
$var wire 1 ! clk $end
$var wire 5 l rd [4:0] $end
$var wire 5 m rs1 [4:0] $end
$var wire 5 n rs2 [4:0] $end
$var wire 1 " rst_n $end
$var wire 1 < wen $end
$var wire 32 o Rd_dat [31:0] $end
$var reg 32 p R1 [31:0] $end
$var reg 32 q R2 [31:0] $end
$var integer 32 r i [31:0] $end
$upscope $end
$scope module _inst_wbmux $end
$var wire 32 s ALU_Result [31:0] $end
$var wire 32 t DMem_Out [31:0] $end
$var wire 32 u Imm_Out [31:0] $end
$var wire 32 v PC [31:0] $end
$var wire 2 w s_mem_to_reg [1:0] $end
$var reg 32 x Data_Out [31:0] $end
$upscope $end
$upscope $end
$upscope $end
$enddefinitions $end
$comment Show the parameter values. $end
$dumpall
b100 ;
b11 :
b0 9
b1 8
b10 7
$end
#0
$dumpvars
b0 x
b1 w
b0 v
b0 u
b0 t
b0 s
b100000 r
b0 q
b0 p
b0 o
b0 n
b0 m
b0 l
b0 k
b0 j
0i
b0 h
b0 g
b0 f
b0 e
b0 d
0c
b0 b
b0 a
b0 `
b11111111111111111111 _
b0 ^
b0 ]
b0 \
b100000000 [
b0 Z
b0 Y
b0 X
b0 W
b0 V
b0 U
b1 T
b1 S
b0 R
b0 Q
0P
0O
0N
0M
0L
0K
0J
1I
b0 H
0G
0F
0E
b1 D
b0 C
b0 B
b0 A
0@
0?
0>
b0 =
0<
b0 6
b0 5
b0 4
b0 3
b0 2
b0 1
b0 0
b0 /
0.
0-
x,
b1 +
0*
1)
0(
1'
b1 &
0%
b0 $
1#
0"
0!
$end
#2
0,
b1 ^
1"
b100000000 [
b100000 r
1!
#4
0!
#6
1I
0'
b0 &
b0 T
b0 w
b0 +
b0 D
b0 S
b10011 e
b10011 Q
b10011 V
b1010 l
1,
b0 ^
b10100010011 3
b10100010011 ]
b10100010011 a
1!
#8
0!
#10
0,
b1 ^
b1 =
1!
#12
0!
#14
b10 =
1,
b0 ^
1!
#16
0!
#18
0,
b1 ^
b11 =
1!
#20
0!
#22
b100 =
1,
b0 ^
1!
#24
0!
#26
b100 1
b100 \
b100 k
b100 v
0,
b1 ^
b0 =
1>
1<
1!
#28
0!
#30
b1010 4
b1010 o
b1010 x
b1010 6
b1010 H
b1010 X
b1010 s
b1010 B
b1010 2
b1010 d
b1010 g
b1010 u
b1011 l
b1010 n
0>
0<
1,
b0 ^
b101000000000010110010011 3
b101000000000010110010011 ]
b101000000000010110010011 a
1!
#32
0!
#34
0,
b1 ^
b1 =
1!
#36
0!
#38
b10 =
1,
b0 ^
1!
#40
0!
#42
0,
b1 ^
b11 =
1!
#44
0!
#46
b100 =
1,
b0 ^
1!
#48
0!
#50
b1000 1
b1000 \
b1000 k
b1000 v
0,
b1 ^
b0 =
1>
1<
1!
#52
0!
#54
1G
0i
0.
1O
0F
0E
b11111111111111111111111111110110 4
b11111111111111111111111111110110 o
b11111111111111111111111111110110 x
1(
0)
0#
b11 +
b11 D
b11 S
b1 $
b1 U
b1 h
b11111111111111111111111111110110 6
b11111111111111111111111111110110 H
b11111111111111111111111111110110 X
b11111111111111111111111111110110 s
b1010 B
b100 b
b100 f
b100 R
b100 W
0N
0I
b1010 /
b1010 Y
b1010 q
b1100 2
b1100 d
b1100 g
b1100 u
b1100011 e
b1100011 Q
b1100011 V
b10101 C
b1100 l
b1011 n
b1010 m
0>
0<
1,
b0 ^
b101101010101011001100011 3
b101101010101011001100011 ]
b101101010101011001100011 a
1!
#56
0!
#58
0,
b1 ^
b1 =
1!
#60
0!
#62
b10 =
1,
b0 ^
1!
#64
0!
#66
0,
b1 ^
b11 =
1!
#68
0!
#70
b100 =
1,
b0 ^
1!
#72
0!
#74
b1100 1
b1100 \
b1100 k
b1100 v
0,
b1 ^
b0 =
1>
1!
#76
0!
#78
1I
0G
b1 4
b1 o
b1 x
1#
1)
0(
b0 +
b0 D
b0 S
b0 $
b0 U
b0 h
b1 6
b1 H
b1 X
b1 s
b1 B
b0 b
b0 f
b0 R
b0 W
0O
b0 /
b0 Y
b0 q
b1 2
b1 d
b1 g
b1 u
b10011 e
b10011 Q
b10011 V
b0 C
b1010 l
b1 n
0>
1,
b0 ^
b101010000010100010011 3
b101010000010100010011 ]
b101010000010100010011 a
1!
#80
0!
#82
0,
b1 ^
b1 =
1!
#84
0!
#86
b10 =
1,
b0 ^
1!
#88
0!
#90
0,
b1 ^
b11 =
1!
#92
0!
#94
b100 =
1,
b0 ^
1!
#96
0!
#98
b10000 1
b10000 \
b10000 k
b10000 v
0,
b1 ^
b0 =
1>
1<
1!
#100
0!
#102
b10 +
b10 D
b10 S
b10 $
b10 U
b10 h
b0 6
b0 H
b0 X
b0 s
b10100 4
b10100 o
b10100 x
b11111111111111111111111111111000 B
b10 b
b10 f
b10 &
b10 T
b10 w
b10 R
b10 W
0J
0I
b11111111111111111111111111111000 2
b11111111111111111111111111111000 d
b11111111111111111111111111111000 g
b11111111111111111111111111111000 u
1c
b1101111 e
b1101111 Q
b1101111 V
b11111 C
b0 l
b11001 n
b11111 m
0>
0<
1,
b0 ^
b11111111100111111111000001101111 3
b11111111100111111111000001101111 ]
b11111111100111111111000001101111 a
1!
#104
0!
#106
0,
b1 ^
b1 =
1!
#108
0!
#110
b10 =
1,
b0 ^
1!
#112
0!
#114
0,
b1 ^
b11 =
1!
#116
0!
#118
b100 =
1,
b0 ^
1!
#120
0!
#122
b1100 4
b1100 o
b1100 x
b1000 1
b1000 \
b1000 k
b1000 v
0,
b1 ^
b0 =
1>
1<
1!
#124
0!
#126
1G
0i
0.
b11111111111111111111111111110111 6
b11111111111111111111111111110111 H
b11111111111111111111111111110111 X
b11111111111111111111111111110111 s
0F
0E
1O
0#
0)
1(
b11 +
b11 D
b11 S
b1 $
b1 U
b1 h
b11111111111111111111111111110111 4
b11111111111111111111111111110111 o
b11111111111111111111111111110111 x
b1 A
b1010 B
b100 b
b100 f
b100 R
b100 W
b0 &
b0 T
b0 w
b1010 /
b1010 Y
b1010 q
b1 0
b1 j
b1 p
b1100 2
b1100 d
b1100 g
b1100 u
0c
b1100011 e
b1100011 Q
b1100011 V
b10101 C
b1100 l
b1011 n
b1010 m
0>
0<
1,
b0 ^
b101101010101011001100011 3
b101101010101011001100011 ]
b101101010101011001100011 a
1!
#128
0!
#130
0,
b1 ^
b1 =
1!
#132
0!
#134
b10 =
1,
b0 ^
1!
#136
0!
#138
0,
b1 ^
b11 =
1!
#140
0!
#142
b100 =
1,
b0 ^
1!
#144
0!
#146
b1100 1
b1100 \
b1100 k
b1100 v
0,
b1 ^
b0 =
1>
1!
#148
0!
#150
1I
0G
b10 4
b10 o
b10 x
0(
1)
1#
b0 +
b0 D
b0 S
b0 $
b0 U
b0 h
b10 6
b10 H
b10 X
b10 s
b1 B
b0 b
b0 f
b0 R
b0 W
0O
b0 /
b0 Y
b0 q
b1 2
b1 d
b1 g
b1 u
b10011 e
b10011 Q
b10011 V
b0 C
b1010 l
b1 n
0>
1,
b0 ^
b101010000010100010011 3
b101010000010100010011 ]
b101010000010100010011 a
1!
#152
0!
#154
0,
b1 ^
b1 =
1!
#156
0!
#158
b10 =
1,
b0 ^
1!
#160
0!
#162
0,
b1 ^
b11 =
1!
#164
0!
#166
b100 =
1,
b0 ^
1!
#168
0!
#170
b10000 1
b10000 \
b10000 k
b10000 v
0,
b1 ^
b0 =
1>
1<
1!
#172
0!
#174
b10 +
b10 D
b10 S
b10 $
b10 U
b10 h
b0 6
b0 H
b0 X
b0 s
b10100 4
b10100 o
b10100 x
b0 A
b11111111111111111111111111111000 B
b10 b
b10 f
b10 R
b10 W
b10 &
b10 T
b10 w
0J
0I
b0 0
b0 j
b0 p
b11111111111111111111111111111000 2
b11111111111111111111111111111000 d
b11111111111111111111111111111000 g
b11111111111111111111111111111000 u
1c
b1101111 e
b1101111 Q
b1101111 V
b11111 C
b0 l
b11001 n
b11111 m
0>
0<
1,
b0 ^
b11111111100111111111000001101111 3
b11111111100111111111000001101111 ]
b11111111100111111111000001101111 a
1!
#176
0!
#178
0,
b1 ^
b1 =
1!
#180
0!
#182
b10 =
1,
b0 ^
1!
#184
0!
#186
0,
b1 ^
b11 =
1!
#188
0!
#190
b100 =
1,
b0 ^
1!
#192
0!
#194
b1100 4
b1100 o
b1100 x
b1000 1
b1000 \
b1000 k
b1000 v
0,
b1 ^
b0 =
1>
1<
1!
#196
0!
#198
1G
0i
0.
b11111111111111111111111111111000 6
b11111111111111111111111111111000 H
b11111111111111111111111111111000 X
b11111111111111111111111111111000 s
0F
0E
1O
1(
0)
0#
b11 +
b11 D
b11 S
b1 $
b1 U
b1 h
b11111111111111111111111111111000 4
b11111111111111111111111111111000 o
b11111111111111111111111111111000 x
b10 A
b1010 B
b100 b
b100 f
b0 &
b0 T
b0 w
b100 R
b100 W
b1010 /
b1010 Y
b1010 q
b10 0
b10 j
b10 p
b1100 2
b1100 d
b1100 g
b1100 u
0c
b1100011 e
b1100011 Q
b1100011 V
b10101 C
b1100 l
b1011 n
b1010 m
0>
0<
1,
b0 ^
b101101010101011001100011 3
b101101010101011001100011 ]
b101101010101011001100011 a
1!
#200
0!
#202
0,
b1 ^
b1 =
1!
#204
0!
#206
b10 =
1,
b0 ^
1!
#208
0!
#210
0,
b1 ^
b11 =
1!
#212
0!
#214
b100 =
1,
b0 ^
1!
#216
0!
#218
b1100 1
b1100 \
b1100 k
b1100 v
0,
b1 ^
b0 =
1>
1!
#220
0!
#222
1I
0G
b11 4
b11 o
b11 x
1#
1)
0(
b0 +
b0 D
b0 S
b0 $
b0 U
b0 h
b11 6
b11 H
b11 X
b11 s
b1 B
b0 b
b0 f
b0 R
b0 W
0O
b0 /
b0 Y
b0 q
b1 2
b1 d
b1 g
b1 u
b10011 e
b10011 Q
b10011 V
b0 C
b1010 l
b1 n
0>
1,
b0 ^
b101010000010100010011 3
b101010000010100010011 ]
b101010000010100010011 a
1!
#224
0!
#226
0,
b1 ^
b1 =
1!
#228
0!
#230
b10 =
1,
b0 ^
1!
#232
0!
#234
0,
b1 ^
b11 =
1!
#236
0!
#238
b100 =
1,
b0 ^
1!
#240
0!
#242
b10000 1
b10000 \
b10000 k
b10000 v
0,
b1 ^
b0 =
1>
1<
1!
#244
0!
#246
b10 +
b10 D
b10 S
b10 $
b10 U
b10 h
b0 6
b0 H
b0 X
b0 s
b10100 4
b10100 o
b10100 x
b0 A
b11111111111111111111111111111000 B
b10 b
b10 f
b10 &
b10 T
b10 w
b10 R
b10 W
0J
0I
b0 0
b0 j
b0 p
b11111111111111111111111111111000 2
b11111111111111111111111111111000 d
b11111111111111111111111111111000 g
b11111111111111111111111111111000 u
1c
b1101111 e
b1101111 Q
b1101111 V
b11111 C
b0 l
b11001 n
b11111 m
0>
0<
1,
b0 ^
b11111111100111111111000001101111 3
b11111111100111111111000001101111 ]
b11111111100111111111000001101111 a
1!
#248
0!
#250
0,
b1 ^
b1 =
1!
#252
0!
#254
b10 =
1,
b0 ^
1!
#256
0!
#258
0,
b1 ^
b11 =
1!
#260
0!
#262
b100 =
1,
b0 ^
1!
#264
0!
#266
b1100 4
b1100 o
b1100 x
b1000 1
b1000 \
b1000 k
b1000 v
0,
b1 ^
b0 =
1>
1<
1!
#268
0!
#270
1G
0i
0.
b11111111111111111111111111111001 6
b11111111111111111111111111111001 H
b11111111111111111111111111111001 X
b11111111111111111111111111111001 s
0F
0E
1O
0#
0)
1(
b11 +
b11 D
b11 S
b1 $
b1 U
b1 h
b11111111111111111111111111111001 4
b11111111111111111111111111111001 o
b11111111111111111111111111111001 x
b11 A
b1010 B
b100 b
b100 f
b100 R
b100 W
b0 &
b0 T
b0 w
b1010 /
b1010 Y
b1010 q
b11 0
b11 j
b11 p
b1100 2
b1100 d
b1100 g
b1100 u
0c
b1100011 e
b1100011 Q
b1100011 V
b10101 C
b1100 l
b1011 n
b1010 m
0>
0<
1,
b0 ^
b101101010101011001100011 3
b101101010101011001100011 ]
b101101010101011001100011 a
1!
