IMem_Interface.v
module IMem_Interface(
    input clk,
    input [31:0] PC,
    output reg rdy,  // instr ready.
    output reg [31:0] INSTR=0
);

reg [31:0] I_Cache [0:255];

initial begin
    $readmemh("I_Cache_Test.hex",I_Cache);
end

reg [3:0] counter=0;
always @(posedge clk) begin
    if(counter==1)begin
        INSTR<=I_Cache[PC];
        counter<=0;
        rdy<=1;
    end
    else begin
        INSTR<=INSTR;
        counter<=counter+1;
        rdy<=0;
    end
end

endmodule

core/PC_Control.v
module PC_Control(
    input clk,
    input [1:0] PC_Sel,  //branch:PC=PC+Imm.  jal:PC=PC+imm.  jalr:PC=R_rs1+Imm
    // if PC_Sel==00(default),PC=PC+4.  else if 01: branch PC = PC + Imm or PC + 4 else if 10: PC=PC+Imm.
    // 11:PC=R_rs1+Imm.
    input s_branch, //if 1,branch jump.
    input [31:0]  Imm,
    input [31:0] R_rs1,
    output reg [31:0] PC=0
);

always @(posedge clk) begin
    case(PC_Sel)
        2'b00:begin
            PC<=PC+4;
        end
        2'b01:begin
            PC<=(s_branch)?PC+Imm:PC+4;
        end
        2'b10:begin
            PC<=PC+Imm;
        end
        2'b11:begin
            PC<=R_rs1+Imm;
        end
    endcase
end

endmodule

CPU_Top.v
module CPU_Top(
    input clk
);

reg [2:0] cpu_state=0;
localparam IF = 0;
localparam ID = 1;
localparam EX = 2;
localparam MEM = 3;
localparam WB = 4;
reg pc_clk=0;
wire imem_rdy;
wire [31:0] PC;
wire [31:0] INSTR;

PC_Control _inst_pc(
    pc_clk,
    2'b00,
    1'b0,
    32'd0,
    32'd0,
    PC
);

IMem_Interface _inst_imem(
    clk,
    PC,
    imem_rdy,
    INSTR
);

always @(posedge clk) begin
    case(cpu_state)
        IF:begin
            pc_clk<=0;

            if(imem_rdy)begin
                cpu_state<=ID;
            end
        end
        ID:
            cpu_state<=EX;
        EX:
            cpu_state<=MEM;
        MEM:
            cpu_state<=WB;
        WB:
            begin
                pc_clk<=1;
                cpu_state<=IF;
            end
    endcase
end

endmodule

Top_tb.v
module Top_tb();
reg clk=0;
always #1 clk=~clk;

CPU_Top _inst_cpu_top(
    clk
);
initial begin
        #1000 $finish;
end

initial begin
        $dumpfile("cpu_top.vcd");
        $dumpvars(0,Top_tb);
end

endmodule

cpu_top.vcd
$date
	Sun Sep 03 00:20:40 2023
$end
$version
	Icarus Verilog
$end
$timescale
	1s
$end
$scope module Top_tb $end
$var reg 1 ! clk $end
$scope module _inst_cpu_top $end
$var wire 1 ! clk $end
$var wire 1 " imem_rdy $end
$var wire 32 # PC [31:0] $end
$var wire 32 $ INSTR [31:0] $end
$var parameter 32 % EX $end
$var parameter 32 & ID $end
$var parameter 32 ' IF $end
$var parameter 32 ( MEM $end
$var parameter 32 ) WB $end
$var reg 3 * cpu_state [2:0] $end
$var reg 1 + pc_clk $end
$scope module _inst_imem $end
$var wire 1 ! clk $end
$var wire 32 , PC [31:0] $end
$var reg 32 - INSTR [31:0] $end
$var reg 4 . counter [3:0] $end
$var reg 1 " rdy $end
$upscope $end
$scope module _inst_pc $end
$var wire 32 / Imm [31:0] $end
$var wire 2 0 PC_Sel [1:0] $end
$var wire 32 1 R_rs1 [31:0] $end
$var wire 1 + clk $end
$var wire 1 2 s_branch $end
$var reg 32 3 PC [31:0] $end
$upscope $end
$upscope $end
$upscope $end
$enddefinitions $end
$comment Show the parameter values. $end
$dumpall
b100 )
b11 (
b0 '
b1 &
b10 %
$end
#0
$dumpvars
b0 3
02
b0 1
b0 0
b0 /
b0 .
b0 -
b0 ,
0+
b0 *
b0 $
b0 #
x"
0!
$end
#1
0"
b1 .
1!
#2
0!
#3
b10 .
1!
#4
0!
#5
b11 .
1!
#6
0!
#7
1"
b0 .
b1111 $
b1111 -
1!
#8
0!
#9
0"
b1 .
b1 *
1!
#10
0!
#11
b10 *
b10 .
1!
#12
0!
#13
b11 .
b11 *
1!
#14
0!
#15
b100 *
1"
b0 .
1!
#16
0!
#17
b100 #
b100 ,
b100 3
0"
b1 .
b0 *
1+
1!
#18
0!
#19
0+
b10 .
1!
#20
0!
#21
b11 .
1!
#22
0!
#23
1"
b0 .
b100 $
b100 -
1!
#24
0!
#25
0"
b1 .
b1 *
1!
#26
0!
#27
b10 *
b10 .
1!
#28
0!
#29
b11 .
b11 *
1!
#30
0!
#31
b100 *
1"
b0 .
1!
#32
0!
#33
b1000 #
b1000 ,
b1000 3
0"
b1 .
b0 *
1+
1!
#34
0!
#35
0+
b10 .
1!
#36
0!
#37
b11 .
1!
#38
0!
#39
1"
b0 .
b1000 $
b1000 -
1!
#40
0!
#41
0"
b1 .
b1 *
1!
#42
0!
#43
b10 *
b10 .
1!
#44
0!
#45
b11 .
b11 *
1!
#46
0!
#47
b100 *
1"
b0 .
1!
#48
0!
#49
b1100 #
b1100 ,
b1100 3
0"
b1 .
b0 *
1+
1!
#50
0!
#51
0+
b10 .
1!
#52
0!
#53
b11 .
1!
#54
0!
#55
1"
b0 .
b1 $
b1 -
1!
#56
0!
#57
0"
b1 .
b1 *
1!
#58
0!
#59
b10 *
b10 .
1!
#60
0!
#61
b11 .
b11 *
1!
#62
0!
#63
b100 *
1"
b0 .
1!
#64
0!
#65
b10000 #
b10000 ,
b10000 3
0"
b1 .
b0 *
1+
1!
#66
0!
#67
0+
b10 .
1!
#68
0!
#69
b11 .
1!
#70
0!
#71
1"
b0 .
b101 $
b101 -
1!
#72
0!
#73
0"
b1 .
b1 *
1!
#74
0!
#75
b10 *
b10 .
1!
#76
0!
#77
b11 .
b11 *
1!
#78
0!
#79
b100 *
1"
b0 .
1!
#80
0!
#81
b10100 #
b10100 ,
b10100 3
0"
b1 .
b0 *
1+
1!
#82
0!
#83
0+
b10 .
1!
#84
0!
#85
b11 .
1!
#86
0!
#87
1"
b0 .
b1001 $
b1001 -
1!
#88
0!
#89
0"
b1 .
b1 *
1!
#90
0!
#91
b10 *
b10 .
1!
#92
0!
#93
b11 .
b11 *
1!
#94
0!
#95
b100 *
1"
b0 .
1!
#96
0!
#97
b11000 #
b11000 ,
b11000 3
0"
b1 .
b0 *
1+
1!
#98
0!
#99
0+
b10 .
1!
#100
0!
#101
b11 .
1!
#102
0!
#103
1"
b0 .
b10 $
b10 -
1!
#104
0!
#105
0"
b1 .
b1 *
1!
#106
0!
#107
b10 *
b10 .
1!
#108
0!
#109
b11 .
b11 *
1!
#110
0!
#111
b100 *
1"
b0 .
1!
#112
0!
#113
b11100 #
b11100 ,
b11100 3
0"
b1 .
b0 *
1+
1!
#114
0!
#115
0+
b10 .
1!
#116
0!
#117
b11 .
1!
#118
0!
#119
1"
b0 .
b110 $
b110 -
1!
#120
0!
#121
0"
b1 .
b1 *
1!
#122
0!
#123
b10 *
b10 .
1!
#124
0!
#125
b11 .
b11 *
1!
#126
0!
#127
b100 *
1"
b0 .
1!
#128
0!
#129
b100000 #
b100000 ,
b100000 3
0"
b1 .
b0 *
1+
1!
#130
0!
#131
0+
b10 .
1!
#132
0!
#133
b11 .
1!
#134
0!
#135
1"
b0 .
b1010 $
b1010 -
1!
#136
0!
#137
0"
b1 .
b1 *
1!
#138
0!
#139
b10 *
b10 .
1!
#140
0!
#141
b11 .
b11 *
1!
#142
0!
#143
b100 *
1"
b0 .
1!
#144
0!
#145
b100100 #
b100100 ,
b100100 3
0"
b1 .
b0 *
1+
1!
#146
0!
#147
0+
b10 .
1!
#148
0!
#149
b11 .
1!
#150
0!
#151
1"
b0 .
b11 $
b11 -
1!
#152
0!
#153
0"
b1 .
b1 *
1!
#154
0!
#155
b10 *
b10 .
1!
#156
0!
#157
b11 .
b11 *
1!
#158
0!
#159
b100 *
1"
b0 .
1!
#160
0!
#161
b101000 #
b101000 ,
b101000 3
0"
b1 .
b0 *
1+
1!
#162
0!
#163
0+
b10 .
1!
#164
0!
#165
b11 .
1!
#166
0!
#167
1"
b0 .
b111 $
b111 -
1!
#168
0!
#169
0"
b1 .
b1 *
1!
#170
0!
#171
b10 *
b10 .
1!
#172
0!
#173
b11 .
b11 *
1!
#174
0!
#175
b100 *
1"
b0 .
1!
#176
0!
#177
b101100 #
b101100 ,
b101100 3
0"
b1 .
b0 *
1+
1!
#178
0!
#179
0+
b10 .
1!
#180
0!
#181
b11 .
1!
#182
0!
#183
1"
b0 .
b0 $
b0 -
1!
#184
0!
#185
0"
b1 .
b1 *
1!
#186
0!
#187
b10 *
b10 .
1!
#188
0!
#189
b11 .
b11 *
1!
#190
0!
#191
b100 *
1"
b0 .
1!
#192
0!
#193
b110000 #
b110000 ,
b110000 3
0"
b1 .
b0 *
1+
1!
#194
0!
#195
0+
b10 .
1!
#196
0!
#197
b11 .
1!
#198
0!
#199
1"
b0 .
b100 $
b100 -
1!
#200
0!
#201
0"
b1 .
b1 *
1!
#202
0!
#203
b10 *
b10 .
1!
#204
0!
#205
b11 .
b11 *
1!
#206
0!
#207
b100 *
1"
b0 .
1!
#208
0!
#209
b110100 #
b110100 ,
b110100 3
0"
b1 .
b0 *
1+
1!
#210
0!
#211
0+
b10 .
1!
#212
0!
#213
b11 .
1!
#214
0!
#215
1"
b0 .
b1000 $
b1000 -
1!
#216
0!
#217
0"
b1 .
b1 *
1!
#218
0!
#219
b10 *
b10 .
1!
#220
0!
#221
b11 .
b11 *
1!
#222
0!
#223
b100 *
1"
b0 .
1!
#224
0!
#225
b111000 #
b111000 ,
b111000 3
0"
b1 .
b0 *
1+
1!
#226
0!
#227
0+
b10 .
1!
#228
0!
#229
b11 .
1!
#230
0!
#231
1"
b0 .
b1 $
b1 -
1!
#232
0!
#233
0"
b1 .
b1 *
1!
#234
0!
#235
b10 *
b10 .
1!
#236
0!
#237
b11 .
b11 *
1!
#238
0!
#239
b100 *
1"
b0 .
1!
#240
0!
#241
b111100 #
b111100 ,
b111100 3
0"
b1 .
b0 *
1+
1!
#242
0!
#243
0+
b10 .
1!
#244
0!
#245
b11 .
1!
#246
0!
#247
1"
b0 .
b101 $
b101 -
1!
#248
0!
#249
0"
b1 .
b1 *
1!
#250
0!
#251
b10 *
b10 .
1!
#252
0!
#253
b11 .
b11 *
1!
#254
0!
#255
b100 *
1"
b0 .
1!
#256
0!
#257
b1000000 #
b1000000 ,
b1000000 3
0"
b1 .
b0 *
1+
1!
#258
0!
#259
0+
b10 .
1!
#260
0!
#261
b11 .
1!
#262
0!
#263
1"
b0 .
b1001 $
b1001 -
1!
#264
0!
#265
0"
b1 .
b1 *
1!
#266
0!
#267
b10 *
b10 .
1!
#268
0!
#269
b11 .
b11 *
1!
#270
0!
#271
b100 *
1"
b0 .
1!
#272
0!
#273
b1000100 #
b1000100 ,
b1000100 3
0"
b1 .
b0 *
1+
1!
#274
0!
#275
0+
b10 .
1!
#276
0!
#277
b11 .
1!
#278
0!
#279
1"
b0 .
b10 $
b10 -
1!
#280
0!
#281
0"
b1 .
b1 *
1!
#282
0!
#283
b10 *
b10 .
1!
#284
0!
#285
b11 .
b11 *
1!
#286
0!
#287
b100 *
1"
b0 .
1!
#288
0!
#289
b1001000 #
b1001000 ,
b1001000 3
0"
b1 .
b0 *
1+
1!
#290
0!
#291
0+
b10 .
1!
#292
0!
#293
b11 .
1!
#294
0!
#295
1"
b0 .
b110 $
b110 -
1!
#296
0!
#297
0"
b1 .
b1 *
1!
#298
0!
#299
b10 *
b10 .
1!
#300
0!
#301
b11 .
b11 *
1!
#302
0!
#303
b100 *
1"
b0 .
1!
#304
0!
#305
b1001100 #
b1001100 ,
b1001100 3
0"
b1 .
b0 *
1+
1!
#306
0!
#307
0+
b10 .
1!
#308
0!
#309
b11 .
1!
#310
0!
#311
1"
b0 .
b1010 $
b1010 -
1!
#312
0!
#313
0"
b1 .
b1 *
1!
#314
0!
#315
b10 *
b10 .
1!
#316
0!
#317
b11 .
b11 *
1!
#318
0!
#319
b100 *
1"
b0 .
1!
#320
0!
#321
b1010000 #
b1010000 ,
b1010000 3
0"
b1 .
b0 *
1+
1!
#322
0!
#323
0+
b10 .
1!
#324
0!
#325
b11 .
1!
#326
0!
#327
1"
b0 .
b11 $
b11 -
1!
#328
0!
#329
0"
b1 .
b1 *
1!
#330
0!
#331
b10 *
b10 .
1!
#332
0!
#333
b11 .
b11 *
1!
#334
0!
#335
b100 *
1"
b0 .
1!
#336
0!
#337
b1010100 #
b1010100 ,
b1010100 3
0"
b1 .
b0 *
1+
1!
#338
0!
#339
0+
b10 .
1!
#340
0!
#341
b11 .
1!
#342
0!
#343
1"
b0 .
b111 $
b111 -
1!
#344
0!
#345
0"
b1 .
b1 *
1!
#346
0!
#347
b10 *
b10 .
1!
#348
0!
#349
b11 .
b11 *
1!
#350
0!
#351
b100 *
1"
b0 .
1!
#352
0!
#353
b1011000 #
b1011000 ,
b1011000 3
0"
b1 .
b0 *
1+
1!
#354
0!
#355
0+
b10 .
1!
#356
0!
#357
b11 .
1!
#358
0!
#359
1"
b0 .
b0 $
b0 -
1!
#360
0!
#361
0"
b1 .
b1 *
1!
#362
0!
#363
b10 *
b10 .
1!
#364
0!
#365
b11 .
b11 *
1!
#366
0!
#367
b100 *
1"
b0 .
1!
#368
0!
#369
b1011100 #
b1011100 ,
b1011100 3
0"
b1 .
b0 *
1+
1!
#370
0!
#371
0+
b10 .
1!
#372
0!
#373
b11 .
1!
#374
0!
#375
1"
b0 .
b100 $
b100 -
1!
#376
0!
#377
0"
b1 .
b1 *
1!
#378
0!
#379
b10 *
b10 .
1!
#380
0!
#381
b11 .
b11 *
1!
#382
0!
#383
b100 *
1"
b0 .
1!
#384
0!
#385
b1100000 #
b1100000 ,
b1100000 3
0"
b1 .
b0 *
1+
1!
#386
0!
#387
0+
b10 .
1!
#388
0!
#389
b11 .
1!
#390
0!
#391
1"
b0 .
b1000 $
b1000 -
1!
#392
0!
#393
0"
b1 .
b1 *
1!
#394
0!
#395
b10 *
b10 .
1!
#396
0!
#397
b11 .
b11 *
1!
#398
0!
#399
b100 *
1"
b0 .
1!
#400
0!
#401
b1100100 #
b1100100 ,
b1100100 3
0"
b1 .
b0 *
1+
1!
#402
0!
#403
0+
b10 .
1!
#404
0!
#405
b11 .
1!
#406
0!
#407
1"
b0 .
b1 $
b1 -
1!
#408
0!
#409
0"
b1 .
b1 *
1!
#410
0!
#411
b10 *
b10 .
1!
#412
0!
#413
b11 .
b11 *
1!
#414
0!
#415
b100 *
1"
b0 .
1!
#416
0!
#417
b1101000 #
b1101000 ,
b1101000 3
0"
b1 .
b0 *
1+
1!
#418
0!
#419
0+
b10 .
1!
#420
0!
#421
b11 .
1!
#422
0!
#423
1"
b0 .
b101 $
b101 -
1!
#424
0!
#425
0"
b1 .
b1 *
1!
#426
0!
#427
b10 *
b10 .
1!
#428
0!
#429
b11 .
b11 *
1!
#430
0!
#431
b100 *
1"
b0 .
1!
#432
0!
#433
b1101100 #
b1101100 ,
b1101100 3
0"
b1 .
b0 *
1+
1!
#434
0!
#435
0+
b10 .
1!
#436
0!
#437
b11 .
1!
#438
0!
#439
1"
b0 .
b1001 $
b1001 -
1!
#440
0!
#441
0"
b1 .
b1 *
1!
#442
0!
#443
b10 *
b10 .
1!
#444
0!
#445
b11 .
b11 *
1!
#446
0!
#447
b100 *
1"
b0 .
1!
#448
0!
#449
b1110000 #
b1110000 ,
b1110000 3
0"
b1 .
b0 *
1+
1!
#450
0!
#451
0+
b10 .
1!
#452
0!
#453
b11 .
1!
#454
0!
#455
1"
b0 .
b10 $
b10 -
1!
#456
0!
#457
0"
b1 .
b1 *
1!
#458
0!
#459
b10 *
b10 .
1!
#460
0!
#461
b11 .
b11 *
1!
#462
0!
#463
b100 *
1"
b0 .
1!
#464
0!
#465
b1110100 #
b1110100 ,
b1110100 3
0"
b1 .
b0 *
1+
1!
#466
0!
#467
0+
b10 .
1!
#468
0!
#469
b11 .
1!
#470
0!
#471
1"
b0 .
b110 $
b110 -
1!
#472
0!
#473
0"
b1 .
b1 *
1!
#474
0!
#475
b10 *
b10 .
1!
#476
0!
#477
b11 .
b11 *
1!
#478
0!
#479
b100 *
1"
b0 .
1!
#480
0!
#481
b1111000 #
b1111000 ,
b1111000 3
0"
b1 .
b0 *
1+
1!
#482
0!
#483
0+
b10 .
1!
#484
0!
#485
b11 .
1!
#486
0!
#487
1"
b0 .
b1010 $
b1010 -
1!
#488
0!
#489
0"
b1 .
b1 *
1!
#490
0!
#491
b10 *
b10 .
1!
#492
0!
#493
b11 .
b11 *
1!
#494
0!
#495
b100 *
1"
b0 .
1!
#496
0!
#497
b1111100 #
b1111100 ,
b1111100 3
0"
b1 .
b0 *
1+
1!
#498
0!
#499
0+
b10 .
1!
#500
0!
#501
b11 .
1!
#502
0!
#503
1"
b0 .
b11 $
b11 -
1!
#504
0!
#505
0"
b1 .
b1 *
1!
#506
0!
#507
b10 *
b10 .
1!
#508
0!
#509
b11 .
b11 *
1!
#510
0!
#511
b100 *
1"
b0 .
1!
#512
0!
#513
b10000000 #
b10000000 ,
b10000000 3
0"
b1 .
b0 *
1+
1!
#514
0!
#515
0+
b10 .
1!
#516
0!
#517
b11 .
1!
#518
0!
#519
1"
b0 .
b111 $
b111 -
1!
#520
0!
#521
0"
b1 .
b1 *
1!
#522
0!
#523
b10 *
b10 .
1!
#524
0!
#525
b11 .
b11 *
1!
#526
0!
#527
b100 *
1"
b0 .
1!
#528
0!
#529
b10000100 #
b10000100 ,
b10000100 3
0"
b1 .
b0 *
1+
1!
#530
0!
#531
0+
b10 .
1!
#532
0!
#533
b11 .
1!
#534
0!
#535
1"
b0 .
b0 $
b0 -
1!
#536
0!
#537
0"
b1 .
b1 *
1!
#538
0!
#539
b10 *
b10 .
1!
#540
0!
#541
b11 .
b11 *
1!
#542
0!
#543
b100 *
1"
b0 .
1!
#544
0!
#545
b10001000 #
b10001000 ,
b10001000 3
0"
b1 .
b0 *
1+
1!
#546
0!
#547
0+
b10 .
1!
#548
0!
#549
b11 .
1!
#550
0!
#551
1"
b0 .
b100 $
b100 -
1!
#552
0!
#553
0"
b1 .
b1 *
1!
#554
0!
#555
b10 *
b10 .
1!
#556
0!
#557
b11 .
b11 *
1!
#558
0!
#559
b100 *
1"
b0 .
1!
#560
0!
#561
b10001100 #
b10001100 ,
b10001100 3
0"
b1 .
b0 *
1+
1!
#562
0!
#563
0+
b10 .
1!
#564
0!
#565
b11 .
1!
#566
0!
#567
1"
b0 .
b1000 $
b1000 -
1!
#568
0!
#569
0"
b1 .
b1 *
1!
#570
0!
#571
b10 *
b10 .
1!
#572
0!
#573
b11 .
b11 *
1!
#574
0!
#575
b100 *
1"
b0 .
1!
#576
0!
#577
b10010000 #
b10010000 ,
b10010000 3
0"
b1 .
b0 *
1+
1!
#578
0!
#579
0+
b10 .
1!
#580
0!
#581
b11 .
1!
#582
0!
#583
1"
b0 .
b1 $
b1 -
1!
#584
0!
#585
0"
b1 .
b1 *
1!
#586
0!
#587
b10 *
b10 .
1!
#588
0!
#589
b11 .
b11 *
1!
#590
0!
#591
b100 *
1"
b0 .
1!
#592
0!
#593
b10010100 #
b10010100 ,
b10010100 3
0"
b1 .
b0 *
1+
1!
#594
0!
#595
0+
b10 .
1!
#596
0!
#597
b11 .
1!
#598
0!
#599
1"
b0 .
b101 $
b101 -
1!
#600
0!
#601
0"
b1 .
b1 *
1!
#602
0!
#603
b10 *
b10 .
1!
#604
0!
#605
b11 .
b11 *
1!
#606
0!
#607
b100 *
1"
b0 .
1!
#608
0!
#609
b10011000 #
b10011000 ,
b10011000 3
0"
b1 .
b0 *
1+
1!
#610
0!
#611
0+
b10 .
1!
#612
0!
#613
b11 .
1!
#614
0!
#615
1"
b0 .
b1001 $
b1001 -
1!
#616
0!
#617
0"
b1 .
b1 *
1!
#618
0!
#619
b10 *
b10 .
1!
#620
0!
#621
b11 .
b11 *
1!
#622
0!
#623
b100 *
1"
b0 .
1!
#624
0!
#625
b10011100 #
b10011100 ,
b10011100 3
0"
b1 .
b0 *
1+
1!
#626
0!
#627
0+
b10 .
1!
#628
0!
#629
b11 .
1!
#630
0!
#631
1"
b0 .
b10 $
b10 -
1!
#632
0!
#633
0"
b1 .
b1 *
1!
#634
0!
#635
b10 *
b10 .
1!
#636
0!
#637
b11 .
b11 *
1!
#638
0!
#639
b100 *
1"
b0 .
1!
#640
0!
#641
b10100000 #
b10100000 ,
b10100000 3
0"
b1 .
b0 *
1+
1!
#642
0!
#643
0+
b10 .
1!
#644
0!
#645
b11 .
1!
#646
0!
#647
1"
b0 .
b110 $
b110 -
1!
#648
0!
#649
0"
b1 .
b1 *
1!
#650
0!
#651
b10 *
b10 .
1!
#652
0!
#653
b11 .
b11 *
1!
#654
0!
#655
b100 *
1"
b0 .
1!
#656
0!
#657
b10100100 #
b10100100 ,
b10100100 3
0"
b1 .
b0 *
1+
1!
#658
0!
#659
0+
b10 .
1!
#660
0!
#661
b11 .
1!
#662
0!
#663
1"
b0 .
b1010 $
b1010 -
1!
#664
0!
#665
0"
b1 .
b1 *
1!
#666
0!
#667
b10 *
b10 .
1!
#668
0!
#669
b11 .
b11 *
1!
#670
0!
#671
b100 *
1"
b0 .
1!
#672
0!
#673
b10101000 #
b10101000 ,
b10101000 3
0"
b1 .
b0 *
1+
1!
#674
0!
#675
0+
b10 .
1!
#676
0!
#677
b11 .
1!
#678
0!
#679
1"
b0 .
b11 $
b11 -
1!
#680
0!
#681
0"
b1 .
b1 *
1!
#682
0!
#683
b10 *
b10 .
1!
#684
0!
#685
b11 .
b11 *
1!
#686
0!
#687
b100 *
1"
b0 .
1!
#688
0!
#689
b10101100 #
b10101100 ,
b10101100 3
0"
b1 .
b0 *
1+
1!
#690
0!
#691
0+
b10 .
1!
#692
0!
#693
b11 .
1!
#694
0!
#695
1"
b0 .
b111 $
b111 -
1!
#696
0!
#697
0"
b1 .
b1 *
1!
#698
0!
#699
b10 *
b10 .
1!
#700
0!
#701
b11 .
b11 *
1!
#702
0!
#703
b100 *
1"
b0 .
1!
#704
0!
#705
b10110000 #
b10110000 ,
b10110000 3
0"
b1 .
b0 *
1+
1!
#706
0!
#707
0+
b10 .
1!
#708
0!
#709
b11 .
1!
#710
0!
#711
1"
b0 .
b0 $
b0 -
1!
#712
0!
#713
0"
b1 .
b1 *
1!
#714
0!
#715
b10 *
b10 .
1!
#716
0!
#717
b11 .
b11 *
1!
#718
0!
#719
b100 *
1"
b0 .
1!
#720
0!
#721
b10110100 #
b10110100 ,
b10110100 3
0"
b1 .
b0 *
1+
1!
#722
0!
#723
0+
b10 .
1!
#724
0!
#725
b11 .
1!
#726
0!
#727
1"
b0 .
b100 $
b100 -
1!
#728
0!
#729
0"
b1 .
b1 *
1!
#730
0!
#731
b10 *
b10 .
1!
#732
0!
#733
b11 .
b11 *
1!
#734
0!
#735
b100 *
1"
b0 .
1!
#736
0!
#737
b10111000 #
b10111000 ,
b10111000 3
0"
b1 .
b0 *
1+
1!
#738
0!
#739
0+
b10 .
1!
#740
0!
#741
b11 .
1!
#742
0!
#743
1"
b0 .
b1000 $
b1000 -
1!
#744
0!
#745
0"
b1 .
b1 *
1!
#746
0!
#747
b10 *
b10 .
1!
#748
0!
#749
b11 .
b11 *
1!
#750
0!
#751
b100 *
1"
b0 .
1!
#752
0!
#753
b10111100 #
b10111100 ,
b10111100 3
0"
b1 .
b0 *
1+
1!
#754
0!
#755
0+
b10 .
1!
#756
0!
#757
b11 .
1!
#758
0!
#759
1"
b0 .
b1 $
b1 -
1!
#760
0!
#761
0"
b1 .
b1 *
1!
#762
0!
#763
b10 *
b10 .
1!
#764
0!
#765
b11 .
b11 *
1!
#766
0!
#767
b100 *
1"
b0 .
1!
#768
0!
#769
b11000000 #
b11000000 ,
b11000000 3
0"
b1 .
b0 *
1+
1!
#770
0!
#771
0+
b10 .
1!
#772
0!
#773
b11 .
1!
#774
0!
#775
1"
b0 .
b101 $
b101 -
1!
#776
0!
#777
0"
b1 .
b1 *
1!
#778
0!
#779
b10 *
b10 .
1!
#780
0!
#781
b11 .
b11 *
1!
#782
0!
#783
b100 *
1"
b0 .
1!
#784
0!
#785
b11000100 #
b11000100 ,
b11000100 3
0"
b1 .
b0 *
1+
1!
#786
0!
#787
0+
b10 .
1!
#788
0!
#789
b11 .
1!
#790
0!
#791
1"
b0 .
b1001 $
b1001 -
1!
#792
0!
#793
0"
b1 .
b1 *
1!
#794
0!
#795
b10 *
b10 .
1!
#796
0!
#797
b11 .
b11 *
1!
#798
0!
#799
b100 *
1"
b0 .
1!
#800
0!
#801
b11001000 #
b11001000 ,
b11001000 3
0"
b1 .
b0 *
1+
1!
#802
0!
#803
0+
b10 .
1!
#804
0!
#805
b11 .
1!
#806
0!
#807
1"
b0 .
b10 $
b10 -
1!
#808
0!
#809
0"
b1 .
b1 *
1!
#810
0!
#811
b10 *
b10 .
1!
#812
0!
#813
b11 .
b11 *
1!
#814
0!
#815
b100 *
1"
b0 .
1!
#816
0!
#817
b11001100 #
b11001100 ,
b11001100 3
0"
b1 .
b0 *
1+
1!
#818
0!
#819
0+
b10 .
1!
#820
0!
#821
b11 .
1!
#822
0!
#823
1"
b0 .
b110 $
b110 -
1!
#824
0!
#825
0"
b1 .
b1 *
1!
#826
0!
#827
b10 *
b10 .
1!
#828
0!
#829
b11 .
b11 *
1!
#830
0!
#831
b100 *
1"
b0 .
1!
#832
0!
#833
b11010000 #
b11010000 ,
b11010000 3
0"
b1 .
b0 *
1+
1!
#834
0!
#835
0+
b10 .
1!
#836
0!
#837
b11 .
1!
#838
0!
#839
1"
b0 .
b1010 $
b1010 -
1!
#840
0!
#841
0"
b1 .
b1 *
1!
#842
0!
#843
b10 *
b10 .
1!
#844
0!
#845
b11 .
b11 *
1!
#846
0!
#847
b100 *
1"
b0 .
1!
#848
0!
#849
b11010100 #
b11010100 ,
b11010100 3
0"
b1 .
b0 *
1+
1!
#850
0!
#851
0+
b10 .
1!
#852
0!
#853
b11 .
1!
#854
0!
#855
1"
b0 .
b11 $
b11 -
1!
#856
0!
#857
0"
b1 .
b1 *
1!
#858
0!
#859
b10 *
b10 .
1!
#860
0!
#861
b11 .
b11 *
1!
#862
0!
#863
b100 *
1"
b0 .
1!
#864
0!
#865
b11011000 #
b11011000 ,
b11011000 3
0"
b1 .
b0 *
1+
1!
#866
0!
#867
0+
b10 .
1!
#868
0!
#869
b11 .
1!
#870
0!
#871
1"
b0 .
b111 $
b111 -
1!
#872
0!
#873
0"
b1 .
b1 *
1!
#874
0!
#875
b10 *
b10 .
1!
#876
0!
#877
b11 .
b11 *
1!
#878
0!
#879
b100 *
1"
b0 .
1!
#880
0!
#881
b11011100 #
b11011100 ,
b11011100 3
0"
b1 .
b0 *
1+
1!
#882
0!
#883
0+
b10 .
1!
#884
0!
#885
b11 .
1!
#886
0!
#887
1"
b0 .
b0 $
b0 -
1!
#888
0!
#889
0"
b1 .
b1 *
1!
#890
0!
#891
b10 *
b10 .
1!
#892
0!
#893
b11 .
b11 *
1!
#894
0!
#895
b100 *
1"
b0 .
1!
#896
0!
#897
b11100000 #
b11100000 ,
b11100000 3
0"
b1 .
b0 *
1+
1!
#898
0!
#899
0+
b10 .
1!
#900
0!
#901
b11 .
1!
#902
0!
#903
1"
b0 .
b100 $
b100 -
1!
#904
0!
#905
0"
b1 .
b1 *
1!
#906
0!
#907
b10 *
b10 .
1!
#908
0!
#909
b11 .
b11 *
1!
#910
0!
#911
b100 *
1"
b0 .
1!
#912
0!
#913
b11100100 #
b11100100 ,
b11100100 3
0"
b1 .
b0 *
1+
1!
#914
0!
#915
0+
b10 .
1!
#916
0!
#917
b11 .
1!
#918
0!
#919
1"
b0 .
b1000 $
b1000 -
1!
#920
0!
#921
0"
b1 .
b1 *
1!
#922
0!
#923
b10 *
b10 .
1!
#924
0!
#925
b11 .
b11 *
1!
#926
0!
#927
b100 *
1"
b0 .
1!
#928
0!
#929
b11101000 #
b11101000 ,
b11101000 3
0"
b1 .
b0 *
1+
1!
#930
0!
#931
0+
b10 .
1!
#932
0!
#933
b11 .
1!
#934
0!
#935
1"
b0 .
b1 $
b1 -
1!
#936
0!
#937
0"
b1 .
b1 *
1!
#938
0!
#939
b10 *
b10 .
1!
#940
0!
#941
b11 .
b11 *
1!
#942
0!
#943
b100 *
1"
b0 .
1!
#944
0!
#945
b11101100 #
b11101100 ,
b11101100 3
0"
b1 .
b0 *
1+
1!
#946
0!
#947
0+
b10 .
1!
#948
0!
#949
b11 .
1!
#950
0!
#951
1"
b0 .
b101 $
b101 -
1!
#952
0!
#953
0"
b1 .
b1 *
1!
#954
0!
#955
b10 *
b10 .
1!
#956
0!
#957
b11 .
b11 *
1!
#958
0!
#959
b100 *
1"
b0 .
1!
#960
0!
#961
b11110000 #
b11110000 ,
b11110000 3
0"
b1 .
b0 *
1+
1!
#962
0!
#963
0+
b10 .
1!
#964
0!
#965
b11 .
1!
#966
0!
#967
1"
b0 .
b1001 $
b1001 -
1!
#968
0!
#969
0"
b1 .
b1 *
1!
#970
0!
#971
b10 *
b10 .
1!
#972
0!
#973
b11 .
b11 *
1!
#974
0!
#975
b100 *
1"
b0 .
1!
#976
0!
#977
b11110100 #
b11110100 ,
b11110100 3
0"
b1 .
b0 *
1+
1!
#978
0!
#979
0+
b10 .
1!
#980
0!
#981
b11 .
1!
#982
0!
#983
1"
b0 .
b10 $
b10 -
1!
#984
0!
#985
0"
b1 .
b1 *
1!
#986
0!
#987
b10 *
b10 .
1!
#988
0!
#989
b11 .
b11 *
1!
#990
0!
#991
b100 *
1"
b0 .
1!
#992
0!
#993
b11111000 #
b11111000 ,
b11111000 3
0"
b1 .
b0 *
1+
1!
#994
0!
#995
0+
b10 .
1!
#996
0!
#997
b11 .
1!
#998
0!
#999
1"
b0 .
b110 $
b110 -
1!
