core/DMem_Interface.v
module DMem_Interface(
    input clk,
    input rst_n,
    input  wen,
    input  ren,
    input [31:0] wd,
    input [31:0] addr,
    output reg [31:0] rd_out=0,
    output reg dmem_rdy=0
);
reg [7:0] D_Cache [0:255];

always@(*)begin
    if(ren)begin
        rd_out<={D_Cache[addr],D_Cache[addr+1],D_Cache[addr+2],D_Cache[addr+3]};
        dmem_rdy<=1;
    end
    else begin
        rd_out<=rd_out;
        dmem_rdy<=0;
    end
end

integer i;
always@(posedge clk or negedge rst_n) begin
    if(!rst_n) begin
        for(i=0;i<256;i++) D_Cache[i]<=0;
    end
    else if(wen)begin
        D_Cache[addr]  <=wd[24+:8];
        D_Cache[addr+1]<=wd[16+:8];
        D_Cache[addr+2]<=wd[8+:8];
        D_Cache[addr+3]<=wd[0+:8];
    end
end

endmodule

testbench/DMem_tb.v
module DMem_tb (
);
reg clk=0;
reg rst_n=1;
reg wen=0;
reg ren=0;
reg [31:0] wd=0;
reg [31:0] addr=0;
wire [31:0] out;
wire rdy;
DMem_Interface _inst_test_dmem(
    clk,
    rst_n,
    wen,
    ren,
    wd,
    addr,
    out,
    rdy
);
initial begin
        $dumpfile("DMem_tb.vcd");
        $dumpvars(0,DMem_tb);
end
always #1 clk=~clk;

initial
begin
    #1
    rst_n<=0;
    #1
    rst_n<=1;
    // write
    #2 addr<=32'd8;
    wd  <=32'd100;
    #1 wen<=1;
    #2 wen<=0;

    //read
    #2 addr<=32'd8;
    #2 ren <= 1;
    #2 ren <= 0;
    #10 $finish;
end

endmodule

DMem_tb.vcd
$date
	Sun Sep 03 16:38:44 2023
$end
$version
	Icarus Verilog
$end
$timescale
	1s
$end
$scope module DMem_tb $end
$var wire 1 ! rdy $end
$var wire 32 " out [31:0] $end
$var reg 32 # addr [31:0] $end
$var reg 1 $ clk $end
$var reg 1 % ren $end
$var reg 1 & rst_n $end
$var reg 32 ' wd [31:0] $end
$var reg 1 ( wen $end
$scope module _inst_test_dmem $end
$var wire 32 ) addr [31:0] $end
$var wire 1 $ clk $end
$var wire 1 % ren $end
$var wire 1 & rst_n $end
$var wire 32 * wd [31:0] $end
$var wire 1 ( wen $end
$var reg 1 ! dmem_rdy $end
$var reg 32 + rd_out [31:0] $end
$var integer 32 , i [31:0] $end
$upscope $end
$upscope $end
$enddefinitions $end
$comment Show the parameter values. $end
$dumpall
$end
#0
$dumpvars
bx ,
b0 +
b0 *
b0 )
0(
b0 '
1&
0%
0$
b0 #
b0 "
0!
$end
#1
b100000000 ,
0&
1$
#2
1&
0$
#3
1$
#4
b1100100 '
b1100100 *
b1000 #
b1000 )
0$
#5
1(
1$
#6
0$
#7
0(
1$
#8
0$
#9
1$
#10
0$
#11
b1100100 "
b1100100 +
1%
1$
#12
0$
#13
0%
1$
