core/RegFile.v
module RegFile(
    input clk,
    input rst_n,
    input [4:0] rs1,
    input [4:0] rs2,
    input [4:0] rd,
    output reg [31:0] R1=0,
    output reg [31:0] R2=0,
    input wen,
    input [31:0] Rd_dat
);

reg [31:0] regs [0:31];

always@(*)begin
    if(rs1==0)
    begin
        R1<=0;
    end
    // else if(rs1==rd&&wen==1)begin
    //     R1<=Rd_dat;
    // end
    else
        R1<=regs[rs1];
end

always@(*)begin
    if(rs2==0)
    begin
        R2<=0;
    end
    // else if(rs2==rd&&wen==1)begin
    //     R2<=Rd_dat;
    // end
    else
        R2<=regs[rs2];
end

integer i;
always @(posedge clk or negedge rst_n) begin
    if(!rst_n)
    begin
        for(i=0;i<32;i++)
            regs[i]<=0;
    end
    else if(wen&&rd!=0)
    begin
        regs[rd] <= Rd_dat;
    end
end

endmodule

testbench/RegFile_tb.v
module RegFile_tb();
reg clk=0;
always begin
    #1 clk=~clk;
end

reg [4:0] rs1=0;
reg [4:0] rs2=0;
reg [4:0] rd=0;
wire [31:0] R1;
wire [31:0] R2;
reg    wen=0;
reg [31:0] Rd_dat=0;
reg rst_n=1;

RegFile _inst_regfile(
    clk,
    rst_n,
    rs1,
    rs2,
    rd,
    R1,
    R2,
    wen,
    Rd_dat
);

initial begin
    // read x0,x1 -> x3
    #2 rst_n<=0;
    #2 rst_n<=1;
    #2 rs1<=0;
       rs2<=0;
       rd<=3;
    #1 Rd_dat<=32'd1000;
    #2 wen<=1;
    #2 wen<=0;

    #4 rs1<=3;
       rs2<=1;
       rd<=1;
    #1 Rd_dat<=32'd1;
    #1 wen<=1;
    #2 wen<=0;

    #4 rs1<=0;
       rs2<=1;
       rd<=3;
    #1 Rd_dat<=32'd100;
    #1 wen<=1;
    #2 wen<=0;
    #100 $finish;
end

initial begin
        $dumpfile("regfile_tb.vcd");
        $dumpvars(0,RegFile_tb);
end
endmodule

regfile_tb.vcd
$date
	Sun Sep 03 15:18:38 2023
$end
$version
	Icarus Verilog
$end
$timescale
	1s
$end
$scope module RegFile_tb $end
$var wire 32 ! R2 [31:0] $end
$var wire 32 " R1 [31:0] $end
$var reg 32 # Rd_dat [31:0] $end
$var reg 1 $ clk $end
$var reg 5 % rd [4:0] $end
$var reg 5 & rs1 [4:0] $end
$var reg 5 ' rs2 [4:0] $end
$var reg 1 ( rst_n $end
$var reg 1 ) wen $end
$scope module _inst_regfile $end
$var wire 32 * Rd_dat [31:0] $end
$var wire 1 $ clk $end
$var wire 5 + rd [4:0] $end
$var wire 5 , rs1 [4:0] $end
$var wire 5 - rs2 [4:0] $end
$var wire 1 ( rst_n $end
$var wire 1 ) wen $end
$var reg 32 . R1 [31:0] $end
$var reg 32 / R2 [31:0] $end
$var integer 32 0 i [31:0] $end
$upscope $end
$upscope $end
$enddefinitions $end
$comment Show the parameter values. $end
$dumpall
$end
#0
$dumpvars
bx 0
b0 /
b0 .
b0 -
b0 ,
b0 +
b0 *
0)
1(
b0 '
b0 &
b0 %
0$
b0 #
b0 "
b0 !
$end
#1
1$
#2
b100000 0
0(
0$
#3
b100000 0
1$
#4
1(
0$
#5
1$
#6
b11 %
b11 +
0$
#7
b1111101000 #
b1111101000 *
1$
#8
0$
#9
1)
1$
#10
0$
#11
0)
1$
#12
0$
#13
1$
#14
0$
#15
b1111101000 "
b1111101000 .
b1 %
b1 +
b1 '
b1 -
b11 &
b11 ,
1$
#16
b1 #
b1 *
0$
#17
b1 !
b1 /
1)
1$
#18
0$
#19
0)
1$
#20
0$
#21
1$
#22
0$
#23
b0 "
b0 .
b11 %
b11 +
b0 &
b0 ,
1$
#24
b1100100 #
b1100100 *
0$
#25
1)
1$
#26
0$
#27
0)
1$
